<?xml version="1.0" encoding="utf-8" standalone="yes"?>
<Gesture Name = "Circle">
	<Stroke>
		<Point X = "584,9173" Y = "-484,6306" T = "0" Pressure = "0" />
		<Point X = "584,9173" Y = "-484,6306" T = "0" Pressure = "0" />
		<Point X = "584,9173" Y = "-484,6306" T = "0" Pressure = "0" />
		<Point X = "584,9173" Y = "-484,6306" T = "0" Pressure = "0" />
		<Point X = "584,9173" Y = "-484,6306" T = "0" Pressure = "0" />
		<Point X = "584,9173" Y = "-484,6306" T = "0" Pressure = "0" />
		<Point X = "584,9173" Y = "-484,6306" T = "0" Pressure = "0" />
		<Point X = "584,9173" Y = "-484,6306" T = "0" Pressure = "0" />
		<Point X = "584,9173" Y = "-484,6306" T = "0" Pressure = "0" />
		<Point X = "584,9173" Y = "-484,6306" T = "0" Pressure = "0" />
		<Point X = "584,9173" Y = "-484,6306" T = "0" Pressure = "0" />
		<Point X = "584,9173" Y = "-484,6306" T = "0" Pressure = "0" />
		<Point X = "584,9173" Y = "-484,6306" T = "0" Pressure = "0" />
		<Point X = "584,9173" Y = "-484,6306" T = "0" Pressure = "0" />
		<Point X = "584,9173" Y = "-484,6306" T = "0" Pressure = "0" />
		<Point X = "584,9173" Y = "-484,6306" T = "0" Pressure = "0" />
		<Point X = "584,9173" Y = "-484,6306" T = "0" Pressure = "0" />
		<Point X = "584,9173" Y = "-484,6306" T = "0" Pressure = "0" />
		<Point X = "584,9173" Y = "-484,6306" T = "0" Pressure = "0" />
		<Point X = "584,9173" Y = "-484,6306" T = "0" Pressure = "0" />
		<Point X = "584,9173" Y = "-484,6306" T = "0" Pressure = "0" />
		<Point X = "584,9173" Y = "-484,6306" T = "0" Pressure = "0" />
		<Point X = "584,9173" Y = "-484,6306" T = "0" Pressure = "0" />
		<Point X = "584,9173" Y = "-484,6306" T = "0" Pressure = "0" />
		<Point X = "584,9173" Y = "-484,6306" T = "0" Pressure = "0" />
		<Point X = "584,9173" Y = "-484,6306" T = "0" Pressure = "0" />
		<Point X = "584,9173" Y = "-484,6306" T = "0" Pressure = "0" />
		<Point X = "584,9173" Y = "-484,6306" T = "0" Pressure = "0" />
		<Point X = "584,9173" Y = "-484,6306" T = "0" Pressure = "0" />
		<Point X = "584,9173" Y = "-484,6306" T = "0" Pressure = "0" />
	</Stroke>
	<Stroke>
		<Point X = "500,3748" Y = "-804,9393" T = "0" Pressure = "0" />
		<Point X = "500,3748" Y = "-804,9393" T = "0" Pressure = "0" />
		<Point X = "500,3748" Y = "-806,1301" T = "0" Pressure = "0" />
		<Point X = "500,3748" Y = "-806,1301" T = "0" Pressure = "0" />
		<Point X = "500,3748" Y = "-806,1301" T = "0" Pressure = "0" />
		<Point X = "500,3748" Y = "-807,3208" T = "0" Pressure = "0" />
		<Point X = "500,3748" Y = "-807,3208" T = "0" Pressure = "0" />
		<Point X = "500,3748" Y = "-807,3208" T = "0" Pressure = "0" />
		<Point X = "500,3748" Y = "-807,3208" T = "0" Pressure = "0" />
		<Point X = "500,3748" Y = "-808,5115" T = "0" Pressure = "0" />
		<Point X = "500,3748" Y = "-808,5115" T = "0" Pressure = "0" />
		<Point X = "500,3748" Y = "-808,5115" T = "0" Pressure = "0" />
		<Point X = "501,5656" Y = "-808,5115" T = "0" Pressure = "0" />
		<Point X = "501,5656" Y = "-809,7023" T = "0" Pressure = "0" />
		<Point X = "502,7563" Y = "-809,7023" T = "0" Pressure = "0" />
		<Point X = "502,7563" Y = "-809,7023" T = "0" Pressure = "0" />
		<Point X = "502,7563" Y = "-809,7023" T = "0" Pressure = "0" />
		<Point X = "502,7563" Y = "-810,8931" T = "0" Pressure = "0" />
		<Point X = "502,7563" Y = "-812,0838" T = "0" Pressure = "0" />
		<Point X = "503,9471" Y = "-812,0838" T = "0" Pressure = "0" />
		<Point X = "503,9471" Y = "-812,0838" T = "0" Pressure = "0" />
		<Point X = "503,9471" Y = "-813,2745" T = "0" Pressure = "0" />
		<Point X = "505,1378" Y = "-813,2745" T = "0" Pressure = "0" />
		<Point X = "505,1378" Y = "-814,4653" T = "0" Pressure = "0" />
		<Point X = "505,1378" Y = "-814,4653" T = "0" Pressure = "0" />
		<Point X = "506,3286" Y = "-814,4653" T = "0" Pressure = "0" />
		<Point X = "506,3286" Y = "-815,656" T = "0" Pressure = "0" />
		<Point X = "507,5193" Y = "-816,8467" T = "0" Pressure = "0" />
		<Point X = "507,5193" Y = "-816,8467" T = "0" Pressure = "0" />
		<Point X = "508,71" Y = "-818,0375" T = "0" Pressure = "0" />
		<Point X = "508,71" Y = "-818,0375" T = "0" Pressure = "0" />
		<Point X = "508,71" Y = "-818,0375" T = "0" Pressure = "0" />
		<Point X = "509,9008" Y = "-819,2282" T = "0" Pressure = "0" />
		<Point X = "511,0915" Y = "-820,4189" T = "0" Pressure = "0" />
		<Point X = "511,0915" Y = "-820,4189" T = "0" Pressure = "0" />
		<Point X = "511,0915" Y = "-821,6097" T = "0" Pressure = "0" />
		<Point X = "513,473" Y = "-821,6097" T = "0" Pressure = "0" />
		<Point X = "513,473" Y = "-821,6097" T = "0" Pressure = "0" />
		<Point X = "513,473" Y = "-822,8004" T = "0" Pressure = "0" />
		<Point X = "514,6637" Y = "-822,8004" T = "0" Pressure = "0" />
		<Point X = "514,6637" Y = "-823,9911" T = "0" Pressure = "0" />
		<Point X = "515,8545" Y = "-823,9911" T = "0" Pressure = "0" />
		<Point X = "515,8545" Y = "-823,9911" T = "0" Pressure = "0" />
		<Point X = "517,0452" Y = "-823,9911" T = "0" Pressure = "0" />
		<Point X = "518,236" Y = "-826,3726" T = "0" Pressure = "0" />
		<Point X = "518,236" Y = "-826,3726" T = "0" Pressure = "0" />
		<Point X = "518,236" Y = "-826,3726" T = "0" Pressure = "0" />
		<Point X = "519,4267" Y = "-826,3726" T = "0" Pressure = "0" />
		<Point X = "520,6174" Y = "-827,5634" T = "0" Pressure = "0" />
		<Point X = "520,6174" Y = "-827,5634" T = "0" Pressure = "0" />
		<Point X = "520,6174" Y = "-827,5634" T = "0" Pressure = "0" />
		<Point X = "521,8082" Y = "-827,5634" T = "0" Pressure = "0" />
		<Point X = "522,9989" Y = "-828,7542" T = "0" Pressure = "0" />
		<Point X = "522,9989" Y = "-828,7542" T = "0" Pressure = "0" />
		<Point X = "524,1896" Y = "-828,7542" T = "0" Pressure = "0" />
		<Point X = "524,1896" Y = "-828,7542" T = "0" Pressure = "0" />
		<Point X = "525,3804" Y = "-829,9449" T = "0" Pressure = "0" />
		<Point X = "525,3804" Y = "-829,9449" T = "0" Pressure = "0" />
		<Point X = "525,3804" Y = "-829,9449" T = "0" Pressure = "0" />
		<Point X = "526,5711" Y = "-831,1356" T = "0" Pressure = "0" />
		<Point X = "527,7618" Y = "-831,1356" T = "0" Pressure = "0" />
		<Point X = "527,7618" Y = "-831,1356" T = "0" Pressure = "0" />
		<Point X = "528,9526" Y = "-831,1356" T = "0" Pressure = "0" />
		<Point X = "528,9526" Y = "-831,1356" T = "0" Pressure = "0" />
		<Point X = "528,9526" Y = "-832,3264" T = "0" Pressure = "0" />
		<Point X = "530,1433" Y = "-832,3264" T = "0" Pressure = "0" />
		<Point X = "530,1433" Y = "-832,3264" T = "0" Pressure = "0" />
		<Point X = "531,334" Y = "-832,3264" T = "0" Pressure = "0" />
		<Point X = "532,5248" Y = "-832,3264" T = "0" Pressure = "0" />
		<Point X = "532,5248" Y = "-833,5171" T = "0" Pressure = "0" />
		<Point X = "533,7155" Y = "-833,5171" T = "0" Pressure = "0" />
		<Point X = "533,7155" Y = "-833,5171" T = "0" Pressure = "0" />
		<Point X = "534,9063" Y = "-833,5171" T = "0" Pressure = "0" />
		<Point X = "536,097" Y = "-833,5171" T = "0" Pressure = "0" />
		<Point X = "536,097" Y = "-833,5171" T = "0" Pressure = "0" />
		<Point X = "537,2878" Y = "-834,7078" T = "0" Pressure = "0" />
		<Point X = "538,4785" Y = "-834,7078" T = "0" Pressure = "0" />
		<Point X = "539,6693" Y = "-834,7078" T = "0" Pressure = "0" />
		<Point X = "539,6693" Y = "-834,7078" T = "0" Pressure = "0" />
		<Point X = "540,86" Y = "-834,7078" T = "0" Pressure = "0" />
		<Point X = "542,0507" Y = "-834,7078" T = "0" Pressure = "0" />
		<Point X = "543,2415" Y = "-835,8986" T = "0" Pressure = "0" />
		<Point X = "544,4322" Y = "-835,8986" T = "0" Pressure = "0" />
		<Point X = "544,4322" Y = "-835,8986" T = "0" Pressure = "0" />
		<Point X = "545,6229" Y = "-835,8986" T = "0" Pressure = "0" />
		<Point X = "546,8137" Y = "-835,8986" T = "0" Pressure = "0" />
		<Point X = "548,0044" Y = "-837,0893" T = "0" Pressure = "0" />
		<Point X = "549,1951" Y = "-837,0893" T = "0" Pressure = "0" />
		<Point X = "551,5766" Y = "-837,0893" T = "0" Pressure = "0" />
		<Point X = "551,5766" Y = "-837,0893" T = "0" Pressure = "0" />
		<Point X = "552,7673" Y = "-837,0893" T = "0" Pressure = "0" />
		<Point X = "553,9581" Y = "-837,0893" T = "0" Pressure = "0" />
		<Point X = "556,3396" Y = "-837,0893" T = "0" Pressure = "0" />
		<Point X = "556,3396" Y = "-837,0893" T = "0" Pressure = "0" />
		<Point X = "558,7211" Y = "-837,0893" T = "0" Pressure = "0" />
		<Point X = "558,7211" Y = "-837,0893" T = "0" Pressure = "0" />
		<Point X = "561,1025" Y = "-837,0893" T = "0" Pressure = "0" />
		<Point X = "562,2933" Y = "-837,0893" T = "0" Pressure = "0" />
		<Point X = "563,484" Y = "-837,0893" T = "0" Pressure = "0" />
		<Point X = "564,6747" Y = "-837,0893" T = "0" Pressure = "0" />
		<Point X = "565,8655" Y = "-837,0893" T = "0" Pressure = "0" />
		<Point X = "567,0562" Y = "-837,0893" T = "0" Pressure = "0" />
		<Point X = "568,2469" Y = "-837,0893" T = "0" Pressure = "0" />
		<Point X = "569,4377" Y = "-837,0893" T = "0" Pressure = "0" />
		<Point X = "570,6284" Y = "-837,0893" T = "0" Pressure = "0" />
		<Point X = "571,8192" Y = "-835,8986" T = "0" Pressure = "0" />
		<Point X = "573,0099" Y = "-835,8986" T = "0" Pressure = "0" />
		<Point X = "573,0099" Y = "-835,8986" T = "0" Pressure = "0" />
		<Point X = "575,3914" Y = "-835,8986" T = "0" Pressure = "0" />
		<Point X = "575,3914" Y = "-835,8986" T = "0" Pressure = "0" />
		<Point X = "576,5822" Y = "-835,8986" T = "0" Pressure = "0" />
		<Point X = "577,7729" Y = "-834,7078" T = "0" Pressure = "0" />
		<Point X = "578,9636" Y = "-834,7078" T = "0" Pressure = "0" />
		<Point X = "580,1544" Y = "-834,7078" T = "0" Pressure = "0" />
		<Point X = "580,1544" Y = "-834,7078" T = "0" Pressure = "0" />
		<Point X = "581,3451" Y = "-833,5171" T = "0" Pressure = "0" />
		<Point X = "582,5358" Y = "-833,5171" T = "0" Pressure = "0" />
		<Point X = "582,5358" Y = "-833,5171" T = "0" Pressure = "0" />
		<Point X = "583,7266" Y = "-833,5171" T = "0" Pressure = "0" />
		<Point X = "584,9173" Y = "-833,5171" T = "0" Pressure = "0" />
		<Point X = "586,108" Y = "-832,3264" T = "0" Pressure = "0" />
		<Point X = "586,108" Y = "-832,3264" T = "0" Pressure = "0" />
		<Point X = "587,2988" Y = "-832,3264" T = "0" Pressure = "0" />
		<Point X = "588,4895" Y = "-832,3264" T = "0" Pressure = "0" />
		<Point X = "589,6802" Y = "-831,1356" T = "0" Pressure = "0" />
		<Point X = "590,871" Y = "-831,1356" T = "0" Pressure = "0" />
		<Point X = "590,871" Y = "-829,9449" T = "0" Pressure = "0" />
		<Point X = "592,0618" Y = "-829,9449" T = "0" Pressure = "0" />
		<Point X = "593,2525" Y = "-829,9449" T = "0" Pressure = "0" />
		<Point X = "594,4432" Y = "-829,9449" T = "0" Pressure = "0" />
		<Point X = "595,634" Y = "-828,7542" T = "0" Pressure = "0" />
		<Point X = "596,8247" Y = "-828,7542" T = "0" Pressure = "0" />
		<Point X = "596,8247" Y = "-828,7542" T = "0" Pressure = "0" />
		<Point X = "598,0154" Y = "-827,5634" T = "0" Pressure = "0" />
		<Point X = "599,2062" Y = "-827,5634" T = "0" Pressure = "0" />
		<Point X = "600,3969" Y = "-826,3726" T = "0" Pressure = "0" />
		<Point X = "601,5876" Y = "-826,3726" T = "0" Pressure = "0" />
		<Point X = "602,7784" Y = "-825,1819" T = "0" Pressure = "0" />
		<Point X = "605,1599" Y = "-825,1819" T = "0" Pressure = "0" />
		<Point X = "606,3506" Y = "-823,9911" T = "0" Pressure = "0" />
		<Point X = "607,5413" Y = "-823,9911" T = "0" Pressure = "0" />
		<Point X = "607,5413" Y = "-822,8004" T = "0" Pressure = "0" />
		<Point X = "609,9228" Y = "-822,8004" T = "0" Pressure = "0" />
		<Point X = "611,1136" Y = "-821,6097" T = "0" Pressure = "0" />
		<Point X = "611,1136" Y = "-820,4189" T = "0" Pressure = "0" />
		<Point X = "613,4951" Y = "-820,4189" T = "0" Pressure = "0" />
		<Point X = "614,6858" Y = "-819,2282" T = "0" Pressure = "0" />
		<Point X = "615,8765" Y = "-819,2282" T = "0" Pressure = "0" />
		<Point X = "617,0673" Y = "-818,0375" T = "0" Pressure = "0" />
		<Point X = "619,4487" Y = "-816,8467" T = "0" Pressure = "0" />
		<Point X = "619,4487" Y = "-816,8467" T = "0" Pressure = "0" />
		<Point X = "620,6395" Y = "-815,656" T = "0" Pressure = "0" />
		<Point X = "621,8302" Y = "-815,656" T = "0" Pressure = "0" />
		<Point X = "624,2117" Y = "-814,4653" T = "0" Pressure = "0" />
		<Point X = "625,4024" Y = "-813,2745" T = "0" Pressure = "0" />
		<Point X = "625,4024" Y = "-812,0838" T = "0" Pressure = "0" />
		<Point X = "627,7839" Y = "-812,0838" T = "0" Pressure = "0" />
		<Point X = "628,9746" Y = "-810,8931" T = "0" Pressure = "0" />
		<Point X = "630,1654" Y = "-809,7023" T = "0" Pressure = "0" />
		<Point X = "630,1654" Y = "-809,7023" T = "0" Pressure = "0" />
		<Point X = "631,3561" Y = "-808,5115" T = "0" Pressure = "0" />
		<Point X = "632,5469" Y = "-807,3208" T = "0" Pressure = "0" />
		<Point X = "633,7376" Y = "-806,1301" T = "0" Pressure = "0" />
		<Point X = "634,9283" Y = "-806,1301" T = "0" Pressure = "0" />
		<Point X = "637,3098" Y = "-804,9393" T = "0" Pressure = "0" />
		<Point X = "638,5005" Y = "-803,7486" T = "0" Pressure = "0" />
		<Point X = "640,882" Y = "-801,3671" T = "0" Pressure = "0" />
		<Point X = "642,0728" Y = "-801,3671" T = "0" Pressure = "0" />
		<Point X = "643,2635" Y = "-800,1764" T = "0" Pressure = "0" />
		<Point X = "644,4542" Y = "-800,1764" T = "0" Pressure = "0" />
		<Point X = "644,4542" Y = "-798,9857" T = "0" Pressure = "0" />
		<Point X = "645,645" Y = "-798,9857" T = "0" Pressure = "0" />
		<Point X = "648,0264" Y = "-797,7949" T = "0" Pressure = "0" />
		<Point X = "648,0264" Y = "-796,6042" T = "0" Pressure = "0" />
		<Point X = "649,2172" Y = "-795,4135" T = "0" Pressure = "0" />
		<Point X = "649,2172" Y = "-795,4135" T = "0" Pressure = "0" />
		<Point X = "650,408" Y = "-794,2227" T = "0" Pressure = "0" />
		<Point X = "651,5987" Y = "-794,2227" T = "0" Pressure = "0" />
		<Point X = "652,7894" Y = "-793,032" T = "0" Pressure = "0" />
		<Point X = "652,7894" Y = "-791,8412" T = "0" Pressure = "0" />
		<Point X = "653,9802" Y = "-791,8412" T = "0" Pressure = "0" />
		<Point X = "653,9802" Y = "-791,8412" T = "0" Pressure = "0" />
		<Point X = "655,1709" Y = "-790,6505" T = "0" Pressure = "0" />
		<Point X = "656,3616" Y = "-790,6505" T = "0" Pressure = "0" />
		<Point X = "657,5524" Y = "-789,4597" T = "0" Pressure = "0" />
		<Point X = "657,5524" Y = "-789,4597" T = "0" Pressure = "0" />
		<Point X = "658,7431" Y = "-788,269" T = "0" Pressure = "0" />
		<Point X = "658,7431" Y = "-788,269" T = "0" Pressure = "0" />
		<Point X = "658,7431" Y = "-787,0782" T = "0" Pressure = "0" />
		<Point X = "659,9338" Y = "-787,0782" T = "0" Pressure = "0" />
		<Point X = "659,9338" Y = "-785,8875" T = "0" Pressure = "0" />
		<Point X = "659,9338" Y = "-785,8875" T = "0" Pressure = "0" />
		<Point X = "661,1246" Y = "-785,8875" T = "0" Pressure = "0" />
		<Point X = "662,3153" Y = "-784,6968" T = "0" Pressure = "0" />
		<Point X = "662,3153" Y = "-784,6968" T = "0" Pressure = "0" />
		<Point X = "662,3153" Y = "-783,506" T = "0" Pressure = "0" />
		<Point X = "663,506" Y = "-783,506" T = "0" Pressure = "0" />
		<Point X = "663,506" Y = "-782,3153" T = "0" Pressure = "0" />
		<Point X = "663,506" Y = "-782,3153" T = "0" Pressure = "0" />
		<Point X = "663,506" Y = "-782,3153" T = "0" Pressure = "0" />
		<Point X = "663,506" Y = "-782,3153" T = "0" Pressure = "0" />
		<Point X = "664,6968" Y = "-781,1246" T = "0" Pressure = "0" />
		<Point X = "664,6968" Y = "-781,1246" T = "0" Pressure = "0" />
		<Point X = "664,6968" Y = "-779,9338" T = "0" Pressure = "0" />
		<Point X = "664,6968" Y = "-779,9338" T = "0" Pressure = "0" />
		<Point X = "664,6968" Y = "-779,9338" T = "0" Pressure = "0" />
		<Point X = "664,6968" Y = "-778,7431" T = "0" Pressure = "0" />
		<Point X = "665,8875" Y = "-778,7431" T = "0" Pressure = "0" />
		<Point X = "665,8875" Y = "-777,5524" T = "0" Pressure = "0" />
		<Point X = "665,8875" Y = "-777,5524" T = "0" Pressure = "0" />
		<Point X = "667,0782" Y = "-776,3616" T = "0" Pressure = "0" />
		<Point X = "667,0782" Y = "-776,3616" T = "0" Pressure = "0" />
		<Point X = "667,0782" Y = "-776,3616" T = "0" Pressure = "0" />
		<Point X = "667,0782" Y = "-775,1709" T = "0" Pressure = "0" />
		<Point X = "667,0782" Y = "-773,9802" T = "0" Pressure = "0" />
		<Point X = "667,0782" Y = "-773,9802" T = "0" Pressure = "0" />
		<Point X = "668,269" Y = "-772,7894" T = "0" Pressure = "0" />
		<Point X = "668,269" Y = "-771,5986" T = "0" Pressure = "0" />
		<Point X = "668,269" Y = "-770,4079" T = "0" Pressure = "0" />
		<Point X = "668,269" Y = "-770,4079" T = "0" Pressure = "0" />
		<Point X = "668,269" Y = "-770,4079" T = "0" Pressure = "0" />
		<Point X = "669,4598" Y = "-768,0264" T = "0" Pressure = "0" />
		<Point X = "669,4598" Y = "-768,0264" T = "0" Pressure = "0" />
		<Point X = "669,4598" Y = "-766,8357" T = "0" Pressure = "0" />
		<Point X = "669,4598" Y = "-765,645" T = "0" Pressure = "0" />
		<Point X = "670,6505" Y = "-763,2635" T = "0" Pressure = "0" />
		<Point X = "670,6505" Y = "-763,2635" T = "0" Pressure = "0" />
		<Point X = "670,6505" Y = "-762,0728" T = "0" Pressure = "0" />
		<Point X = "670,6505" Y = "-762,0728" T = "0" Pressure = "0" />
		<Point X = "670,6505" Y = "-759,6913" T = "0" Pressure = "0" />
		<Point X = "671,8412" Y = "-758,5005" T = "0" Pressure = "0" />
		<Point X = "671,8412" Y = "-757,3098" T = "0" Pressure = "0" />
		<Point X = "671,8412" Y = "-756,1191" T = "0" Pressure = "0" />
		<Point X = "671,8412" Y = "-756,1191" T = "0" Pressure = "0" />
		<Point X = "673,032" Y = "-753,7376" T = "0" Pressure = "0" />
		<Point X = "673,032" Y = "-752,5469" T = "0" Pressure = "0" />
		<Point X = "673,032" Y = "-751,3561" T = "0" Pressure = "0" />
		<Point X = "673,032" Y = "-751,3561" T = "0" Pressure = "0" />
		<Point X = "673,032" Y = "-748,9746" T = "0" Pressure = "0" />
		<Point X = "673,032" Y = "-747,7839" T = "0" Pressure = "0" />
		<Point X = "673,032" Y = "-746,5931" T = "0" Pressure = "0" />
		<Point X = "674,2227" Y = "-745,4024" T = "0" Pressure = "0" />
		<Point X = "674,2227" Y = "-745,4024" T = "0" Pressure = "0" />
		<Point X = "674,2227" Y = "-743,0209" T = "0" Pressure = "0" />
		<Point X = "674,2227" Y = "-741,8302" T = "0" Pressure = "0" />
		<Point X = "674,2227" Y = "-740,6395" T = "0" Pressure = "0" />
		<Point X = "674,2227" Y = "-739,4487" T = "0" Pressure = "0" />
		<Point X = "674,2227" Y = "-738,258" T = "0" Pressure = "0" />
		<Point X = "674,2227" Y = "-737,0673" T = "0" Pressure = "0" />
		<Point X = "674,2227" Y = "-734,6858" T = "0" Pressure = "0" />
		<Point X = "674,2227" Y = "-734,6858" T = "0" Pressure = "0" />
		<Point X = "674,2227" Y = "-733,495" T = "0" Pressure = "0" />
		<Point X = "674,2227" Y = "-732,3043" T = "0" Pressure = "0" />
		<Point X = "674,2227" Y = "-731,1135" T = "0" Pressure = "0" />
		<Point X = "674,2227" Y = "-729,9228" T = "0" Pressure = "0" />
		<Point X = "675,4135" Y = "-727,5413" T = "0" Pressure = "0" />
		<Point X = "675,4135" Y = "-727,5413" T = "0" Pressure = "0" />
		<Point X = "675,4135" Y = "-725,1599" T = "0" Pressure = "0" />
		<Point X = "675,4135" Y = "-723,9691" T = "0" Pressure = "0" />
		<Point X = "675,4135" Y = "-723,9691" T = "0" Pressure = "0" />
		<Point X = "675,4135" Y = "-722,7784" T = "0" Pressure = "0" />
		<Point X = "675,4135" Y = "-721,5876" T = "0" Pressure = "0" />
		<Point X = "675,4135" Y = "-720,3969" T = "0" Pressure = "0" />
		<Point X = "675,4135" Y = "-719,2062" T = "0" Pressure = "0" />
		<Point X = "675,4135" Y = "-718,0154" T = "0" Pressure = "0" />
		<Point X = "675,4135" Y = "-718,0154" T = "0" Pressure = "0" />
		<Point X = "675,4135" Y = "-716,8247" T = "0" Pressure = "0" />
		<Point X = "675,4135" Y = "-715,634" T = "0" Pressure = "0" />
		<Point X = "675,4135" Y = "-714,4432" T = "0" Pressure = "0" />
		<Point X = "675,4135" Y = "-713,2524" T = "0" Pressure = "0" />
		<Point X = "675,4135" Y = "-712,0617" T = "0" Pressure = "0" />
		<Point X = "675,4135" Y = "-710,871" T = "0" Pressure = "0" />
		<Point X = "675,4135" Y = "-710,871" T = "0" Pressure = "0" />
		<Point X = "675,4135" Y = "-709,6802" T = "0" Pressure = "0" />
		<Point X = "675,4135" Y = "-708,4895" T = "0" Pressure = "0" />
		<Point X = "675,4135" Y = "-708,4895" T = "0" Pressure = "0" />
		<Point X = "675,4135" Y = "-707,2988" T = "0" Pressure = "0" />
		<Point X = "675,4135" Y = "-707,2988" T = "0" Pressure = "0" />
		<Point X = "675,4135" Y = "-704,9173" T = "0" Pressure = "0" />
		<Point X = "675,4135" Y = "-704,9173" T = "0" Pressure = "0" />
		<Point X = "675,4135" Y = "-703,7266" T = "0" Pressure = "0" />
		<Point X = "675,4135" Y = "-702,5358" T = "0" Pressure = "0" />
		<Point X = "675,4135" Y = "-700,1544" T = "0" Pressure = "0" />
		<Point X = "675,4135" Y = "-698,9636" T = "0" Pressure = "0" />
		<Point X = "675,4135" Y = "-698,9636" T = "0" Pressure = "0" />
		<Point X = "674,2227" Y = "-697,7729" T = "0" Pressure = "0" />
		<Point X = "674,2227" Y = "-695,3914" T = "0" Pressure = "0" />
		<Point X = "674,2227" Y = "-695,3914" T = "0" Pressure = "0" />
		<Point X = "674,2227" Y = "-694,2006" T = "0" Pressure = "0" />
		<Point X = "674,2227" Y = "-691,8192" T = "0" Pressure = "0" />
		<Point X = "674,2227" Y = "-690,6284" T = "0" Pressure = "0" />
		<Point X = "673,032" Y = "-689,4377" T = "0" Pressure = "0" />
		<Point X = "673,032" Y = "-688,2469" T = "0" Pressure = "0" />
		<Point X = "673,032" Y = "-688,2469" T = "0" Pressure = "0" />
		<Point X = "671,8412" Y = "-685,8655" T = "0" Pressure = "0" />
		<Point X = "671,8412" Y = "-684,6747" T = "0" Pressure = "0" />
		<Point X = "671,8412" Y = "-683,484" T = "0" Pressure = "0" />
		<Point X = "671,8412" Y = "-682,2933" T = "0" Pressure = "0" />
		<Point X = "670,6505" Y = "-681,1025" T = "0" Pressure = "0" />
		<Point X = "670,6505" Y = "-679,9118" T = "0" Pressure = "0" />
		<Point X = "670,6505" Y = "-677,5303" T = "0" Pressure = "0" />
		<Point X = "670,6505" Y = "-677,5303" T = "0" Pressure = "0" />
		<Point X = "670,6505" Y = "-676,3396" T = "0" Pressure = "0" />
		<Point X = "669,4598" Y = "-675,1488" T = "0" Pressure = "0" />
		<Point X = "669,4598" Y = "-673,9581" T = "0" Pressure = "0" />
		<Point X = "669,4598" Y = "-672,7673" T = "0" Pressure = "0" />
		<Point X = "669,4598" Y = "-671,5766" T = "0" Pressure = "0" />
		<Point X = "669,4598" Y = "-671,5766" T = "0" Pressure = "0" />
		<Point X = "669,4598" Y = "-670,3859" T = "0" Pressure = "0" />
		<Point X = "668,269" Y = "-669,1951" T = "0" Pressure = "0" />
		<Point X = "668,269" Y = "-668,0044" T = "0" Pressure = "0" />
		<Point X = "668,269" Y = "-668,0044" T = "0" Pressure = "0" />
		<Point X = "667,0782" Y = "-666,8137" T = "0" Pressure = "0" />
		<Point X = "667,0782" Y = "-665,6229" T = "0" Pressure = "0" />
		<Point X = "667,0782" Y = "-665,6229" T = "0" Pressure = "0" />
		<Point X = "667,0782" Y = "-663,2415" T = "0" Pressure = "0" />
		<Point X = "667,0782" Y = "-662,0507" T = "0" Pressure = "0" />
		<Point X = "667,0782" Y = "-662,0507" T = "0" Pressure = "0" />
		<Point X = "665,8875" Y = "-660,86" T = "0" Pressure = "0" />
		<Point X = "665,8875" Y = "-660,86" T = "0" Pressure = "0" />
		<Point X = "665,8875" Y = "-658,4785" T = "0" Pressure = "0" />
		<Point X = "664,6968" Y = "-658,4785" T = "0" Pressure = "0" />
		<Point X = "664,6968" Y = "-657,2877" T = "0" Pressure = "0" />
		<Point X = "664,6968" Y = "-657,2877" T = "0" Pressure = "0" />
		<Point X = "664,6968" Y = "-656,097" T = "0" Pressure = "0" />
		<Point X = "664,6968" Y = "-656,097" T = "0" Pressure = "0" />
		<Point X = "663,506" Y = "-653,7155" T = "0" Pressure = "0" />
		<Point X = "662,3153" Y = "-653,7155" T = "0" Pressure = "0" />
		<Point X = "662,3153" Y = "-653,7155" T = "0" Pressure = "0" />
		<Point X = "662,3153" Y = "-652,5248" T = "0" Pressure = "0" />
		<Point X = "662,3153" Y = "-651,334" T = "0" Pressure = "0" />
		<Point X = "661,1246" Y = "-651,334" T = "0" Pressure = "0" />
		<Point X = "661,1246" Y = "-648,9526" T = "0" Pressure = "0" />
		<Point X = "661,1246" Y = "-648,9526" T = "0" Pressure = "0" />
		<Point X = "659,9338" Y = "-647,7618" T = "0" Pressure = "0" />
		<Point X = "659,9338" Y = "-647,7618" T = "0" Pressure = "0" />
		<Point X = "659,9338" Y = "-646,5711" T = "0" Pressure = "0" />
		<Point X = "658,7431" Y = "-645,3804" T = "0" Pressure = "0" />
		<Point X = "657,5524" Y = "-644,1896" T = "0" Pressure = "0" />
		<Point X = "657,5524" Y = "-644,1896" T = "0" Pressure = "0" />
		<Point X = "657,5524" Y = "-642,9989" T = "0" Pressure = "0" />
		<Point X = "656,3616" Y = "-641,8082" T = "0" Pressure = "0" />
		<Point X = "656,3616" Y = "-641,8082" T = "0" Pressure = "0" />
		<Point X = "656,3616" Y = "-640,6174" T = "0" Pressure = "0" />
		<Point X = "655,1709" Y = "-639,4267" T = "0" Pressure = "0" />
		<Point X = "653,9802" Y = "-638,236" T = "0" Pressure = "0" />
		<Point X = "653,9802" Y = "-637,0452" T = "0" Pressure = "0" />
		<Point X = "652,7894" Y = "-635,8544" T = "0" Pressure = "0" />
		<Point X = "652,7894" Y = "-634,6637" T = "0" Pressure = "0" />
		<Point X = "651,5987" Y = "-633,473" T = "0" Pressure = "0" />
		<Point X = "651,5987" Y = "-633,473" T = "0" Pressure = "0" />
		<Point X = "650,408" Y = "-632,2822" T = "0" Pressure = "0" />
		<Point X = "650,408" Y = "-631,0915" T = "0" Pressure = "0" />
		<Point X = "649,2172" Y = "-631,0915" T = "0" Pressure = "0" />
		<Point X = "649,2172" Y = "-628,71" T = "0" Pressure = "0" />
		<Point X = "649,2172" Y = "-628,71" T = "0" Pressure = "0" />
		<Point X = "648,0264" Y = "-627,5193" T = "0" Pressure = "0" />
		<Point X = "646,8357" Y = "-627,5193" T = "0" Pressure = "0" />
		<Point X = "646,8357" Y = "-626,3286" T = "0" Pressure = "0" />
		<Point X = "645,645" Y = "-626,3286" T = "0" Pressure = "0" />
		<Point X = "645,645" Y = "-625,1378" T = "0" Pressure = "0" />
		<Point X = "644,4542" Y = "-623,9471" T = "0" Pressure = "0" />
		<Point X = "644,4542" Y = "-623,9471" T = "0" Pressure = "0" />
		<Point X = "644,4542" Y = "-622,7563" T = "0" Pressure = "0" />
		<Point X = "643,2635" Y = "-622,7563" T = "0" Pressure = "0" />
		<Point X = "642,0728" Y = "-621,5656" T = "0" Pressure = "0" />
		<Point X = "642,0728" Y = "-621,5656" T = "0" Pressure = "0" />
		<Point X = "640,882" Y = "-620,3749" T = "0" Pressure = "0" />
		<Point X = "640,882" Y = "-620,3749" T = "0" Pressure = "0" />
		<Point X = "640,882" Y = "-619,1841" T = "0" Pressure = "0" />
		<Point X = "639,6913" Y = "-619,1841" T = "0" Pressure = "0" />
		<Point X = "638,5005" Y = "-619,1841" T = "0" Pressure = "0" />
		<Point X = "637,3098" Y = "-617,9933" T = "0" Pressure = "0" />
		<Point X = "637,3098" Y = "-617,9933" T = "0" Pressure = "0" />
		<Point X = "637,3098" Y = "-617,9933" T = "0" Pressure = "0" />
		<Point X = "636,1191" Y = "-616,8026" T = "0" Pressure = "0" />
		<Point X = "636,1191" Y = "-616,8026" T = "0" Pressure = "0" />
		<Point X = "634,9283" Y = "-616,8026" T = "0" Pressure = "0" />
		<Point X = "634,9283" Y = "-615,6119" T = "0" Pressure = "0" />
		<Point X = "634,9283" Y = "-615,6119" T = "0" Pressure = "0" />
		<Point X = "633,7376" Y = "-615,6119" T = "0" Pressure = "0" />
		<Point X = "632,5469" Y = "-614,4211" T = "0" Pressure = "0" />
		<Point X = "632,5469" Y = "-614,4211" T = "0" Pressure = "0" />
		<Point X = "632,5469" Y = "-614,4211" T = "0" Pressure = "0" />
		<Point X = "631,3561" Y = "-614,4211" T = "0" Pressure = "0" />
		<Point X = "631,3561" Y = "-613,2304" T = "0" Pressure = "0" />
		<Point X = "631,3561" Y = "-613,2304" T = "0" Pressure = "0" />
		<Point X = "630,1654" Y = "-613,2304" T = "0" Pressure = "0" />
		<Point X = "630,1654" Y = "-613,2304" T = "0" Pressure = "0" />
		<Point X = "630,1654" Y = "-612,0397" T = "0" Pressure = "0" />
		<Point X = "628,9746" Y = "-612,0397" T = "0" Pressure = "0" />
		<Point X = "628,9746" Y = "-612,0397" T = "0" Pressure = "0" />
		<Point X = "628,9746" Y = "-612,0397" T = "0" Pressure = "0" />
		<Point X = "627,7839" Y = "-610,8489" T = "0" Pressure = "0" />
		<Point X = "627,7839" Y = "-610,8489" T = "0" Pressure = "0" />
		<Point X = "627,7839" Y = "-610,8489" T = "0" Pressure = "0" />
		<Point X = "626,5931" Y = "-609,6582" T = "0" Pressure = "0" />
		<Point X = "626,5931" Y = "-609,6582" T = "0" Pressure = "0" />
		<Point X = "626,5931" Y = "-609,6582" T = "0" Pressure = "0" />
		<Point X = "625,4024" Y = "-609,6582" T = "0" Pressure = "0" />
		<Point X = "625,4024" Y = "-609,6582" T = "0" Pressure = "0" />
		<Point X = "625,4024" Y = "-608,4675" T = "0" Pressure = "0" />
		<Point X = "624,2117" Y = "-608,4675" T = "0" Pressure = "0" />
		<Point X = "623,0209" Y = "-608,4675" T = "0" Pressure = "0" />
		<Point X = "623,0209" Y = "-608,4675" T = "0" Pressure = "0" />
		<Point X = "621,8302" Y = "-607,2767" T = "0" Pressure = "0" />
		<Point X = "621,8302" Y = "-607,2767" T = "0" Pressure = "0" />
		<Point X = "620,6395" Y = "-607,2767" T = "0" Pressure = "0" />
		<Point X = "620,6395" Y = "-606,086" T = "0" Pressure = "0" />
		<Point X = "619,4487" Y = "-606,086" T = "0" Pressure = "0" />
		<Point X = "618,258" Y = "-604,8953" T = "0" Pressure = "0" />
		<Point X = "618,258" Y = "-604,8953" T = "0" Pressure = "0" />
		<Point X = "617,0673" Y = "-604,8953" T = "0" Pressure = "0" />
		<Point X = "617,0673" Y = "-604,8953" T = "0" Pressure = "0" />
		<Point X = "615,8765" Y = "-603,7045" T = "0" Pressure = "0" />
		<Point X = "614,6858" Y = "-603,7045" T = "0" Pressure = "0" />
		<Point X = "614,6858" Y = "-603,7045" T = "0" Pressure = "0" />
		<Point X = "613,4951" Y = "-603,7045" T = "0" Pressure = "0" />
		<Point X = "612,3043" Y = "-602,5138" T = "0" Pressure = "0" />
		<Point X = "611,1136" Y = "-602,5138" T = "0" Pressure = "0" />
		<Point X = "611,1136" Y = "-602,5138" T = "0" Pressure = "0" />
		<Point X = "609,9228" Y = "-602,5138" T = "0" Pressure = "0" />
		<Point X = "608,7321" Y = "-601,3231" T = "0" Pressure = "0" />
		<Point X = "607,5413" Y = "-601,3231" T = "0" Pressure = "0" />
		<Point X = "607,5413" Y = "-601,3231" T = "0" Pressure = "0" />
		<Point X = "606,3506" Y = "-601,3231" T = "0" Pressure = "0" />
		<Point X = "605,1599" Y = "-601,3231" T = "0" Pressure = "0" />
		<Point X = "605,1599" Y = "-600,1323" T = "0" Pressure = "0" />
		<Point X = "602,7784" Y = "-598,9415" T = "0" Pressure = "0" />
		<Point X = "602,7784" Y = "-598,9415" T = "0" Pressure = "0" />
		<Point X = "601,5876" Y = "-598,9415" T = "0" Pressure = "0" />
		<Point X = "600,3969" Y = "-598,9415" T = "0" Pressure = "0" />
		<Point X = "599,2062" Y = "-598,9415" T = "0" Pressure = "0" />
		<Point X = "598,0154" Y = "-598,9415" T = "0" Pressure = "0" />
		<Point X = "596,8247" Y = "-597,7508" T = "0" Pressure = "0" />
		<Point X = "596,8247" Y = "-597,7508" T = "0" Pressure = "0" />
		<Point X = "595,634" Y = "-597,7508" T = "0" Pressure = "0" />
		<Point X = "594,4432" Y = "-597,7508" T = "0" Pressure = "0" />
		<Point X = "593,2525" Y = "-596,5601" T = "0" Pressure = "0" />
		<Point X = "592,0618" Y = "-596,5601" T = "0" Pressure = "0" />
		<Point X = "590,871" Y = "-596,5601" T = "0" Pressure = "0" />
		<Point X = "590,871" Y = "-596,5601" T = "0" Pressure = "0" />
		<Point X = "589,6802" Y = "-596,5601" T = "0" Pressure = "0" />
		<Point X = "588,4895" Y = "-596,5601" T = "0" Pressure = "0" />
		<Point X = "588,4895" Y = "-596,5601" T = "0" Pressure = "0" />
		<Point X = "587,2988" Y = "-596,5601" T = "0" Pressure = "0" />
		<Point X = "587,2988" Y = "-595,3693" T = "0" Pressure = "0" />
		<Point X = "586,108" Y = "-595,3693" T = "0" Pressure = "0" />
		<Point X = "584,9173" Y = "-595,3693" T = "0" Pressure = "0" />
		<Point X = "583,7266" Y = "-594,1786" T = "0" Pressure = "0" />
		<Point X = "583,7266" Y = "-594,1786" T = "0" Pressure = "0" />
		<Point X = "583,7266" Y = "-594,1786" T = "0" Pressure = "0" />
		<Point X = "582,5358" Y = "-594,1786" T = "0" Pressure = "0" />
		<Point X = "582,5358" Y = "-594,1786" T = "0" Pressure = "0" />
		<Point X = "581,3451" Y = "-594,1786" T = "0" Pressure = "0" />
		<Point X = "581,3451" Y = "-594,1786" T = "0" Pressure = "0" />
		<Point X = "580,1544" Y = "-594,1786" T = "0" Pressure = "0" />
		<Point X = "578,9636" Y = "-594,1786" T = "0" Pressure = "0" />
		<Point X = "578,9636" Y = "-594,1786" T = "0" Pressure = "0" />
		<Point X = "577,7729" Y = "-594,1786" T = "0" Pressure = "0" />
		<Point X = "577,7729" Y = "-594,1786" T = "0" Pressure = "0" />
		<Point X = "576,5822" Y = "-594,1786" T = "0" Pressure = "0" />
		<Point X = "576,5822" Y = "-594,1786" T = "0" Pressure = "0" />
		<Point X = "575,3914" Y = "-594,1786" T = "0" Pressure = "0" />
		<Point X = "574,2007" Y = "-594,1786" T = "0" Pressure = "0" />
		<Point X = "573,0099" Y = "-594,1786" T = "0" Pressure = "0" />
		<Point X = "573,0099" Y = "-594,1786" T = "0" Pressure = "0" />
		<Point X = "571,8192" Y = "-594,1786" T = "0" Pressure = "0" />
		<Point X = "570,6284" Y = "-594,1786" T = "0" Pressure = "0" />
		<Point X = "569,4377" Y = "-594,1786" T = "0" Pressure = "0" />
		<Point X = "568,2469" Y = "-594,1786" T = "0" Pressure = "0" />
		<Point X = "568,2469" Y = "-594,1786" T = "0" Pressure = "0" />
		<Point X = "567,0562" Y = "-594,1786" T = "0" Pressure = "0" />
		<Point X = "565,8655" Y = "-594,1786" T = "0" Pressure = "0" />
		<Point X = "563,484" Y = "-594,1786" T = "0" Pressure = "0" />
		<Point X = "563,484" Y = "-594,1786" T = "0" Pressure = "0" />
		<Point X = "562,2933" Y = "-594,1786" T = "0" Pressure = "0" />
		<Point X = "561,1025" Y = "-594,1786" T = "0" Pressure = "0" />
		<Point X = "558,7211" Y = "-594,1786" T = "0" Pressure = "0" />
		<Point X = "558,7211" Y = "-594,1786" T = "0" Pressure = "0" />
		<Point X = "557,5303" Y = "-594,1786" T = "0" Pressure = "0" />
		<Point X = "556,3396" Y = "-594,1786" T = "0" Pressure = "0" />
		<Point X = "555,1489" Y = "-594,1786" T = "0" Pressure = "0" />
		<Point X = "553,9581" Y = "-594,1786" T = "0" Pressure = "0" />
		<Point X = "552,7673" Y = "-594,1786" T = "0" Pressure = "0" />
		<Point X = "550,3859" Y = "-594,1786" T = "0" Pressure = "0" />
		<Point X = "549,1951" Y = "-594,1786" T = "0" Pressure = "0" />
		<Point X = "549,1951" Y = "-594,1786" T = "0" Pressure = "0" />
		<Point X = "548,0044" Y = "-594,1786" T = "0" Pressure = "0" />
		<Point X = "545,6229" Y = "-594,1786" T = "0" Pressure = "0" />
		<Point X = "544,4322" Y = "-594,1786" T = "0" Pressure = "0" />
		<Point X = "544,4322" Y = "-594,1786" T = "0" Pressure = "0" />
		<Point X = "543,2415" Y = "-595,3693" T = "0" Pressure = "0" />
		<Point X = "540,86" Y = "-595,3693" T = "0" Pressure = "0" />
		<Point X = "539,6693" Y = "-595,3693" T = "0" Pressure = "0" />
		<Point X = "538,4785" Y = "-595,3693" T = "0" Pressure = "0" />
		<Point X = "537,2878" Y = "-595,3693" T = "0" Pressure = "0" />
		<Point X = "534,9063" Y = "-595,3693" T = "0" Pressure = "0" />
		<Point X = "534,9063" Y = "-596,5601" T = "0" Pressure = "0" />
		<Point X = "533,7155" Y = "-596,5601" T = "0" Pressure = "0" />
		<Point X = "532,5248" Y = "-596,5601" T = "0" Pressure = "0" />
		<Point X = "530,1433" Y = "-596,5601" T = "0" Pressure = "0" />
		<Point X = "528,9526" Y = "-597,7508" T = "0" Pressure = "0" />
		<Point X = "528,9526" Y = "-597,7508" T = "0" Pressure = "0" />
		<Point X = "528,9526" Y = "-597,7508" T = "0" Pressure = "0" />
		<Point X = "526,5711" Y = "-597,7508" T = "0" Pressure = "0" />
		<Point X = "526,5711" Y = "-597,7508" T = "0" Pressure = "0" />
		<Point X = "524,1896" Y = "-597,7508" T = "0" Pressure = "0" />
		<Point X = "524,1896" Y = "-598,9415" T = "0" Pressure = "0" />
		<Point X = "522,9989" Y = "-598,9415" T = "0" Pressure = "0" />
		<Point X = "521,8082" Y = "-600,1323" T = "0" Pressure = "0" />
		<Point X = "520,6174" Y = "-600,1323" T = "0" Pressure = "0" />
		<Point X = "519,4267" Y = "-600,1323" T = "0" Pressure = "0" />
		<Point X = "518,236" Y = "-600,1323" T = "0" Pressure = "0" />
		<Point X = "518,236" Y = "-601,3231" T = "0" Pressure = "0" />
		<Point X = "515,8545" Y = "-601,3231" T = "0" Pressure = "0" />
		<Point X = "515,8545" Y = "-601,3231" T = "0" Pressure = "0" />
		<Point X = "514,6637" Y = "-602,5138" T = "0" Pressure = "0" />
		<Point X = "513,473" Y = "-602,5138" T = "0" Pressure = "0" />
		<Point X = "513,473" Y = "-602,5138" T = "0" Pressure = "0" />
		<Point X = "511,0915" Y = "-602,5138" T = "0" Pressure = "0" />
		<Point X = "511,0915" Y = "-603,7045" T = "0" Pressure = "0" />
		<Point X = "509,9008" Y = "-603,7045" T = "0" Pressure = "0" />
		<Point X = "509,9008" Y = "-603,7045" T = "0" Pressure = "0" />
		<Point X = "507,5193" Y = "-604,8953" T = "0" Pressure = "0" />
		<Point X = "506,3286" Y = "-606,086" T = "0" Pressure = "0" />
		<Point X = "503,9471" Y = "-606,086" T = "0" Pressure = "0" />
		<Point X = "503,9471" Y = "-607,2767" T = "0" Pressure = "0" />
		<Point X = "502,7563" Y = "-607,2767" T = "0" Pressure = "0" />
		<Point X = "501,5656" Y = "-607,2767" T = "0" Pressure = "0" />
		<Point X = "501,5656" Y = "-607,2767" T = "0" Pressure = "0" />
		<Point X = "500,3748" Y = "-608,4675" T = "0" Pressure = "0" />
		<Point X = "500,3748" Y = "-608,4675" T = "0" Pressure = "0" />
		<Point X = "499,1841" Y = "-608,4675" T = "0" Pressure = "0" />
		<Point X = "499,1841" Y = "-608,4675" T = "0" Pressure = "0" />
		<Point X = "497,9934" Y = "-609,6582" T = "0" Pressure = "0" />
		<Point X = "496,8026" Y = "-609,6582" T = "0" Pressure = "0" />
		<Point X = "496,8026" Y = "-610,8489" T = "0" Pressure = "0" />
		<Point X = "496,8026" Y = "-610,8489" T = "0" Pressure = "0" />
		<Point X = "496,8026" Y = "-610,8489" T = "0" Pressure = "0" />
		<Point X = "495,6119" Y = "-610,8489" T = "0" Pressure = "0" />
		<Point X = "495,6119" Y = "-610,8489" T = "0" Pressure = "0" />
		<Point X = "494,4212" Y = "-612,0397" T = "0" Pressure = "0" />
		<Point X = "494,4212" Y = "-612,0397" T = "0" Pressure = "0" />
		<Point X = "493,2304" Y = "-612,0397" T = "0" Pressure = "0" />
		<Point X = "493,2304" Y = "-612,0397" T = "0" Pressure = "0" />
		<Point X = "492,0397" Y = "-613,2304" T = "0" Pressure = "0" />
		<Point X = "492,0397" Y = "-613,2304" T = "0" Pressure = "0" />
		<Point X = "490,8489" Y = "-613,2304" T = "0" Pressure = "0" />
		<Point X = "490,8489" Y = "-613,2304" T = "0" Pressure = "0" />
		<Point X = "490,8489" Y = "-613,2304" T = "0" Pressure = "0" />
		<Point X = "489,6582" Y = "-613,2304" T = "0" Pressure = "0" />
		<Point X = "489,6582" Y = "-614,4211" T = "0" Pressure = "0" />
		<Point X = "489,6582" Y = "-615,6119" T = "0" Pressure = "0" />
		<Point X = "488,4675" Y = "-615,6119" T = "0" Pressure = "0" />
		<Point X = "487,2767" Y = "-615,6119" T = "0" Pressure = "0" />
		<Point X = "487,2767" Y = "-615,6119" T = "0" Pressure = "0" />
		<Point X = "487,2767" Y = "-616,8026" T = "0" Pressure = "0" />
		<Point X = "486,086" Y = "-616,8026" T = "0" Pressure = "0" />
		<Point X = "486,086" Y = "-616,8026" T = "0" Pressure = "0" />
		<Point X = "484,8953" Y = "-617,9933" T = "0" Pressure = "0" />
		<Point X = "484,8953" Y = "-617,9933" T = "0" Pressure = "0" />
		<Point X = "484,8953" Y = "-617,9933" T = "0" Pressure = "0" />
		<Point X = "484,8953" Y = "-617,9933" T = "0" Pressure = "0" />
		<Point X = "483,7045" Y = "-617,9933" T = "0" Pressure = "0" />
		<Point X = "483,7045" Y = "-619,1841" T = "0" Pressure = "0" />
		<Point X = "483,7045" Y = "-619,1841" T = "0" Pressure = "0" />
		<Point X = "482,5138" Y = "-620,3749" T = "0" Pressure = "0" />
		<Point X = "482,5138" Y = "-620,3749" T = "0" Pressure = "0" />
		<Point X = "482,5138" Y = "-620,3749" T = "0" Pressure = "0" />
		<Point X = "481,323" Y = "-620,3749" T = "0" Pressure = "0" />
		<Point X = "481,323" Y = "-620,3749" T = "0" Pressure = "0" />
		<Point X = "481,323" Y = "-621,5656" T = "0" Pressure = "0" />
		<Point X = "480,1323" Y = "-621,5656" T = "0" Pressure = "0" />
		<Point X = "480,1323" Y = "-621,5656" T = "0" Pressure = "0" />
		<Point X = "480,1323" Y = "-621,5656" T = "0" Pressure = "0" />
		<Point X = "478,9416" Y = "-622,7563" T = "0" Pressure = "0" />
		<Point X = "478,9416" Y = "-622,7563" T = "0" Pressure = "0" />
		<Point X = "478,9416" Y = "-622,7563" T = "0" Pressure = "0" />
		<Point X = "478,9416" Y = "-622,7563" T = "0" Pressure = "0" />
		<Point X = "477,7508" Y = "-622,7563" T = "0" Pressure = "0" />
		<Point X = "477,7508" Y = "-623,9471" T = "0" Pressure = "0" />
		<Point X = "476,5601" Y = "-623,9471" T = "0" Pressure = "0" />
		<Point X = "476,5601" Y = "-625,1378" T = "0" Pressure = "0" />
		<Point X = "476,5601" Y = "-625,1378" T = "0" Pressure = "0" />
		<Point X = "476,5601" Y = "-625,1378" T = "0" Pressure = "0" />
		<Point X = "476,5601" Y = "-625,1378" T = "0" Pressure = "0" />
		<Point X = "476,5601" Y = "-625,1378" T = "0" Pressure = "0" />
		<Point X = "476,5601" Y = "-625,1378" T = "0" Pressure = "0" />
		<Point X = "475,3694" Y = "-626,3286" T = "0" Pressure = "0" />
		<Point X = "475,3694" Y = "-626,3286" T = "0" Pressure = "0" />
		<Point X = "475,3694" Y = "-626,3286" T = "0" Pressure = "0" />
		<Point X = "475,3694" Y = "-626,3286" T = "0" Pressure = "0" />
		<Point X = "474,1786" Y = "-627,5193" T = "0" Pressure = "0" />
		<Point X = "474,1786" Y = "-627,5193" T = "0" Pressure = "0" />
		<Point X = "474,1786" Y = "-627,5193" T = "0" Pressure = "0" />
		<Point X = "474,1786" Y = "-627,5193" T = "0" Pressure = "0" />
		<Point X = "474,1786" Y = "-627,5193" T = "0" Pressure = "0" />
		<Point X = "474,1786" Y = "-628,71" T = "0" Pressure = "0" />
		<Point X = "472,9879" Y = "-628,71" T = "0" Pressure = "0" />
		<Point X = "472,9879" Y = "-629,9008" T = "0" Pressure = "0" />
		<Point X = "472,9879" Y = "-629,9008" T = "0" Pressure = "0" />
		<Point X = "471,7971" Y = "-629,9008" T = "0" Pressure = "0" />
		<Point X = "471,7971" Y = "-629,9008" T = "0" Pressure = "0" />
		<Point X = "471,7971" Y = "-629,9008" T = "0" Pressure = "0" />
		<Point X = "471,7971" Y = "-631,0915" T = "0" Pressure = "0" />
		<Point X = "471,7971" Y = "-631,0915" T = "0" Pressure = "0" />
		<Point X = "471,7971" Y = "-631,0915" T = "0" Pressure = "0" />
		<Point X = "471,7971" Y = "-631,0915" T = "0" Pressure = "0" />
		<Point X = "470,6064" Y = "-632,2822" T = "0" Pressure = "0" />
		<Point X = "470,6064" Y = "-632,2822" T = "0" Pressure = "0" />
		<Point X = "470,6064" Y = "-632,2822" T = "0" Pressure = "0" />
		<Point X = "470,6064" Y = "-632,2822" T = "0" Pressure = "0" />
		<Point X = "470,6064" Y = "-633,473" T = "0" Pressure = "0" />
		<Point X = "469,4156" Y = "-633,473" T = "0" Pressure = "0" />
		<Point X = "469,4156" Y = "-634,6637" T = "0" Pressure = "0" />
		<Point X = "469,4156" Y = "-634,6637" T = "0" Pressure = "0" />
		<Point X = "469,4156" Y = "-634,6637" T = "0" Pressure = "0" />
		<Point X = "469,4156" Y = "-635,8544" T = "0" Pressure = "0" />
		<Point X = "469,4156" Y = "-635,8544" T = "0" Pressure = "0" />
		<Point X = "469,4156" Y = "-635,8544" T = "0" Pressure = "0" />
		<Point X = "469,4156" Y = "-635,8544" T = "0" Pressure = "0" />
		<Point X = "468,2249" Y = "-637,0452" T = "0" Pressure = "0" />
		<Point X = "468,2249" Y = "-637,0452" T = "0" Pressure = "0" />
		<Point X = "468,2249" Y = "-637,0452" T = "0" Pressure = "0" />
		<Point X = "467,0342" Y = "-638,236" T = "0" Pressure = "0" />
		<Point X = "467,0342" Y = "-638,236" T = "0" Pressure = "0" />
		<Point X = "467,0342" Y = "-639,4267" T = "0" Pressure = "0" />
		<Point X = "467,0342" Y = "-639,4267" T = "0" Pressure = "0" />
		<Point X = "467,0342" Y = "-640,6174" T = "0" Pressure = "0" />
		<Point X = "467,0342" Y = "-640,6174" T = "0" Pressure = "0" />
		<Point X = "467,0342" Y = "-640,6174" T = "0" Pressure = "0" />
		<Point X = "465,8434" Y = "-641,8082" T = "0" Pressure = "0" />
		<Point X = "465,8434" Y = "-641,8082" T = "0" Pressure = "0" />
		<Point X = "465,8434" Y = "-641,8082" T = "0" Pressure = "0" />
		<Point X = "465,8434" Y = "-642,9989" T = "0" Pressure = "0" />
		<Point X = "465,8434" Y = "-642,9989" T = "0" Pressure = "0" />
		<Point X = "465,8434" Y = "-642,9989" T = "0" Pressure = "0" />
		<Point X = "465,8434" Y = "-644,1896" T = "0" Pressure = "0" />
		<Point X = "465,8434" Y = "-645,3804" T = "0" Pressure = "0" />
		<Point X = "465,8434" Y = "-645,3804" T = "0" Pressure = "0" />
		<Point X = "465,8434" Y = "-645,3804" T = "0" Pressure = "0" />
		<Point X = "464,6527" Y = "-646,5711" T = "0" Pressure = "0" />
		<Point X = "464,6527" Y = "-646,5711" T = "0" Pressure = "0" />
		<Point X = "464,6527" Y = "-646,5711" T = "0" Pressure = "0" />
		<Point X = "464,6527" Y = "-647,7618" T = "0" Pressure = "0" />
		<Point X = "464,6527" Y = "-647,7618" T = "0" Pressure = "0" />
		<Point X = "464,6527" Y = "-647,7618" T = "0" Pressure = "0" />
		<Point X = "464,6527" Y = "-650,1433" T = "0" Pressure = "0" />
		<Point X = "464,6527" Y = "-650,1433" T = "0" Pressure = "0" />
		<Point X = "464,6527" Y = "-650,1433" T = "0" Pressure = "0" />
		<Point X = "464,6527" Y = "-651,334" T = "0" Pressure = "0" />
		<Point X = "463,462" Y = "-651,334" T = "0" Pressure = "0" />
		<Point X = "463,462" Y = "-652,5248" T = "0" Pressure = "0" />
		<Point X = "463,462" Y = "-652,5248" T = "0" Pressure = "0" />
		<Point X = "463,462" Y = "-652,5248" T = "0" Pressure = "0" />
		<Point X = "462,2712" Y = "-653,7155" T = "0" Pressure = "0" />
		<Point X = "462,2712" Y = "-654,9063" T = "0" Pressure = "0" />
		<Point X = "462,2712" Y = "-654,9063" T = "0" Pressure = "0" />
		<Point X = "462,2712" Y = "-654,9063" T = "0" Pressure = "0" />
		<Point X = "462,2712" Y = "-656,097" T = "0" Pressure = "0" />
		<Point X = "462,2712" Y = "-656,097" T = "0" Pressure = "0" />
		<Point X = "462,2712" Y = "-657,2877" T = "0" Pressure = "0" />
		<Point X = "462,2712" Y = "-657,2877" T = "0" Pressure = "0" />
		<Point X = "462,2712" Y = "-657,2877" T = "0" Pressure = "0" />
		<Point X = "462,2712" Y = "-659,6693" T = "0" Pressure = "0" />
		<Point X = "462,2712" Y = "-659,6693" T = "0" Pressure = "0" />
		<Point X = "462,2712" Y = "-660,86" T = "0" Pressure = "0" />
		<Point X = "462,2712" Y = "-660,86" T = "0" Pressure = "0" />
		<Point X = "462,2712" Y = "-660,86" T = "0" Pressure = "0" />
		<Point X = "462,2712" Y = "-662,0507" T = "0" Pressure = "0" />
		<Point X = "462,2712" Y = "-662,0507" T = "0" Pressure = "0" />
		<Point X = "462,2712" Y = "-663,2415" T = "0" Pressure = "0" />
		<Point X = "462,2712" Y = "-664,4322" T = "0" Pressure = "0" />
		<Point X = "461,0805" Y = "-664,4322" T = "0" Pressure = "0" />
		<Point X = "461,0805" Y = "-665,6229" T = "0" Pressure = "0" />
		<Point X = "461,0805" Y = "-665,6229" T = "0" Pressure = "0" />
		<Point X = "461,0805" Y = "-665,6229" T = "0" Pressure = "0" />
		<Point X = "461,0805" Y = "-666,8137" T = "0" Pressure = "0" />
		<Point X = "461,0805" Y = "-666,8137" T = "0" Pressure = "0" />
		<Point X = "461,0805" Y = "-666,8137" T = "0" Pressure = "0" />
		<Point X = "461,0805" Y = "-668,0044" T = "0" Pressure = "0" />
		<Point X = "461,0805" Y = "-669,1951" T = "0" Pressure = "0" />
		<Point X = "461,0805" Y = "-669,1951" T = "0" Pressure = "0" />
		<Point X = "461,0805" Y = "-670,3859" T = "0" Pressure = "0" />
		<Point X = "461,0805" Y = "-670,3859" T = "0" Pressure = "0" />
		<Point X = "461,0805" Y = "-670,3859" T = "0" Pressure = "0" />
		<Point X = "461,0805" Y = "-671,5766" T = "0" Pressure = "0" />
		<Point X = "461,0805" Y = "-671,5766" T = "0" Pressure = "0" />
		<Point X = "461,0805" Y = "-672,7673" T = "0" Pressure = "0" />
		<Point X = "461,0805" Y = "-673,9581" T = "0" Pressure = "0" />
		<Point X = "461,0805" Y = "-673,9581" T = "0" Pressure = "0" />
		<Point X = "461,0805" Y = "-675,1488" T = "0" Pressure = "0" />
		<Point X = "461,0805" Y = "-675,1488" T = "0" Pressure = "0" />
		<Point X = "461,0805" Y = "-675,1488" T = "0" Pressure = "0" />
		<Point X = "461,0805" Y = "-676,3396" T = "0" Pressure = "0" />
		<Point X = "461,0805" Y = "-676,3396" T = "0" Pressure = "0" />
		<Point X = "461,0805" Y = "-676,3396" T = "0" Pressure = "0" />
		<Point X = "461,0805" Y = "-677,5303" T = "0" Pressure = "0" />
		<Point X = "461,0805" Y = "-678,7211" T = "0" Pressure = "0" />
		<Point X = "461,0805" Y = "-678,7211" T = "0" Pressure = "0" />
		<Point X = "461,0805" Y = "-678,7211" T = "0" Pressure = "0" />
		<Point X = "461,0805" Y = "-679,9118" T = "0" Pressure = "0" />
		<Point X = "461,0805" Y = "-679,9118" T = "0" Pressure = "0" />
		<Point X = "461,0805" Y = "-681,1025" T = "0" Pressure = "0" />
		<Point X = "461,0805" Y = "-681,1025" T = "0" Pressure = "0" />
		<Point X = "461,0805" Y = "-681,1025" T = "0" Pressure = "0" />
		<Point X = "461,0805" Y = "-682,2933" T = "0" Pressure = "0" />
		<Point X = "461,0805" Y = "-682,2933" T = "0" Pressure = "0" />
		<Point X = "461,0805" Y = "-683,484" T = "0" Pressure = "0" />
		<Point X = "461,0805" Y = "-684,6747" T = "0" Pressure = "0" />
		<Point X = "461,0805" Y = "-684,6747" T = "0" Pressure = "0" />
		<Point X = "461,0805" Y = "-685,8655" T = "0" Pressure = "0" />
		<Point X = "461,0805" Y = "-685,8655" T = "0" Pressure = "0" />
		<Point X = "461,0805" Y = "-685,8655" T = "0" Pressure = "0" />
		<Point X = "461,0805" Y = "-687,0562" T = "0" Pressure = "0" />
		<Point X = "461,0805" Y = "-687,0562" T = "0" Pressure = "0" />
		<Point X = "461,0805" Y = "-688,2469" T = "0" Pressure = "0" />
		<Point X = "461,0805" Y = "-689,4377" T = "0" Pressure = "0" />
		<Point X = "461,0805" Y = "-690,6284" T = "0" Pressure = "0" />
		<Point X = "461,0805" Y = "-690,6284" T = "0" Pressure = "0" />
		<Point X = "461,0805" Y = "-691,8192" T = "0" Pressure = "0" />
		<Point X = "461,0805" Y = "-691,8192" T = "0" Pressure = "0" />
		<Point X = "461,0805" Y = "-691,8192" T = "0" Pressure = "0" />
		<Point X = "461,0805" Y = "-693,0099" T = "0" Pressure = "0" />
		<Point X = "461,0805" Y = "-694,2006" T = "0" Pressure = "0" />
		<Point X = "461,0805" Y = "-694,2006" T = "0" Pressure = "0" />
		<Point X = "461,0805" Y = "-695,3914" T = "0" Pressure = "0" />
		<Point X = "461,0805" Y = "-695,3914" T = "0" Pressure = "0" />
		<Point X = "461,0805" Y = "-696,5822" T = "0" Pressure = "0" />
		<Point X = "461,0805" Y = "-697,7729" T = "0" Pressure = "0" />
		<Point X = "461,0805" Y = "-698,9636" T = "0" Pressure = "0" />
		<Point X = "461,0805" Y = "-698,9636" T = "0" Pressure = "0" />
		<Point X = "461,0805" Y = "-698,9636" T = "0" Pressure = "0" />
		<Point X = "461,0805" Y = "-700,1544" T = "0" Pressure = "0" />
		<Point X = "461,0805" Y = "-700,1544" T = "0" Pressure = "0" />
		<Point X = "461,0805" Y = "-701,3451" T = "0" Pressure = "0" />
		<Point X = "461,0805" Y = "-701,3451" T = "0" Pressure = "0" />
		<Point X = "461,0805" Y = "-702,5358" T = "0" Pressure = "0" />
		<Point X = "461,0805" Y = "-703,7266" T = "0" Pressure = "0" />
		<Point X = "461,0805" Y = "-704,9173" T = "0" Pressure = "0" />
		<Point X = "461,0805" Y = "-704,9173" T = "0" Pressure = "0" />
		<Point X = "461,0805" Y = "-706,108" T = "0" Pressure = "0" />
		<Point X = "461,0805" Y = "-706,108" T = "0" Pressure = "0" />
		<Point X = "461,0805" Y = "-707,2988" T = "0" Pressure = "0" />
		<Point X = "461,0805" Y = "-708,4895" T = "0" Pressure = "0" />
		<Point X = "461,0805" Y = "-708,4895" T = "0" Pressure = "0" />
		<Point X = "461,0805" Y = "-709,6802" T = "0" Pressure = "0" />
		<Point X = "461,0805" Y = "-710,871" T = "0" Pressure = "0" />
		<Point X = "461,0805" Y = "-710,871" T = "0" Pressure = "0" />
		<Point X = "461,0805" Y = "-712,0617" T = "0" Pressure = "0" />
		<Point X = "461,0805" Y = "-713,2524" T = "0" Pressure = "0" />
		<Point X = "461,0805" Y = "-713,2524" T = "0" Pressure = "0" />
		<Point X = "461,0805" Y = "-714,4432" T = "0" Pressure = "0" />
		<Point X = "461,0805" Y = "-714,4432" T = "0" Pressure = "0" />
		<Point X = "461,0805" Y = "-715,634" T = "0" Pressure = "0" />
		<Point X = "461,0805" Y = "-715,634" T = "0" Pressure = "0" />
		<Point X = "461,0805" Y = "-718,0154" T = "0" Pressure = "0" />
		<Point X = "461,0805" Y = "-718,0154" T = "0" Pressure = "0" />
		<Point X = "461,0805" Y = "-718,0154" T = "0" Pressure = "0" />
		<Point X = "461,0805" Y = "-719,2062" T = "0" Pressure = "0" />
		<Point X = "461,0805" Y = "-719,2062" T = "0" Pressure = "0" />
		<Point X = "461,0805" Y = "-720,3969" T = "0" Pressure = "0" />
		<Point X = "461,0805" Y = "-720,3969" T = "0" Pressure = "0" />
		<Point X = "461,0805" Y = "-721,5876" T = "0" Pressure = "0" />
		<Point X = "461,0805" Y = "-721,5876" T = "0" Pressure = "0" />
		<Point X = "461,0805" Y = "-721,5876" T = "0" Pressure = "0" />
		<Point X = "461,0805" Y = "-721,5876" T = "0" Pressure = "0" />
		<Point X = "461,0805" Y = "-722,7784" T = "0" Pressure = "0" />
		<Point X = "461,0805" Y = "-723,9691" T = "0" Pressure = "0" />
		<Point X = "461,0805" Y = "-723,9691" T = "0" Pressure = "0" />
		<Point X = "461,0805" Y = "-723,9691" T = "0" Pressure = "0" />
		<Point X = "461,0805" Y = "-725,1599" T = "0" Pressure = "0" />
		<Point X = "461,0805" Y = "-726,3506" T = "0" Pressure = "0" />
		<Point X = "461,0805" Y = "-726,3506" T = "0" Pressure = "0" />
		<Point X = "461,0805" Y = "-727,5413" T = "0" Pressure = "0" />
		<Point X = "461,0805" Y = "-728,7321" T = "0" Pressure = "0" />
		<Point X = "461,0805" Y = "-728,7321" T = "0" Pressure = "0" />
		<Point X = "461,0805" Y = "-729,9228" T = "0" Pressure = "0" />
		<Point X = "461,0805" Y = "-729,9228" T = "0" Pressure = "0" />
		<Point X = "461,0805" Y = "-731,1135" T = "0" Pressure = "0" />
		<Point X = "461,0805" Y = "-732,3043" T = "0" Pressure = "0" />
		<Point X = "461,0805" Y = "-733,495" T = "0" Pressure = "0" />
		<Point X = "461,0805" Y = "-733,495" T = "0" Pressure = "0" />
		<Point X = "461,0805" Y = "-734,6858" T = "0" Pressure = "0" />
		<Point X = "461,0805" Y = "-735,8765" T = "0" Pressure = "0" />
		<Point X = "461,0805" Y = "-737,0673" T = "0" Pressure = "0" />
		<Point X = "462,2712" Y = "-738,258" T = "0" Pressure = "0" />
		<Point X = "462,2712" Y = "-738,258" T = "0" Pressure = "0" />
		<Point X = "462,2712" Y = "-739,4487" T = "0" Pressure = "0" />
		<Point X = "462,2712" Y = "-739,4487" T = "0" Pressure = "0" />
		<Point X = "462,2712" Y = "-740,6395" T = "0" Pressure = "0" />
		<Point X = "462,2712" Y = "-741,8302" T = "0" Pressure = "0" />
		<Point X = "462,2712" Y = "-743,0209" T = "0" Pressure = "0" />
		<Point X = "463,462" Y = "-744,2117" T = "0" Pressure = "0" />
		<Point X = "463,462" Y = "-744,2117" T = "0" Pressure = "0" />
		<Point X = "463,462" Y = "-745,4024" T = "0" Pressure = "0" />
		<Point X = "463,462" Y = "-746,5931" T = "0" Pressure = "0" />
		<Point X = "463,462" Y = "-747,7839" T = "0" Pressure = "0" />
		<Point X = "463,462" Y = "-748,9746" T = "0" Pressure = "0" />
		<Point X = "463,462" Y = "-748,9746" T = "0" Pressure = "0" />
		<Point X = "463,462" Y = "-750,1653" T = "0" Pressure = "0" />
		<Point X = "463,462" Y = "-751,3561" T = "0" Pressure = "0" />
		<Point X = "463,462" Y = "-752,5469" T = "0" Pressure = "0" />
		<Point X = "463,462" Y = "-752,5469" T = "0" Pressure = "0" />
		<Point X = "463,462" Y = "-753,7376" T = "0" Pressure = "0" />
		<Point X = "464,6527" Y = "-753,7376" T = "0" Pressure = "0" />
		<Point X = "464,6527" Y = "-754,9283" T = "0" Pressure = "0" />
		<Point X = "464,6527" Y = "-754,9283" T = "0" Pressure = "0" />
		<Point X = "464,6527" Y = "-754,9283" T = "0" Pressure = "0" />
		<Point X = "464,6527" Y = "-756,1191" T = "0" Pressure = "0" />
		<Point X = "464,6527" Y = "-756,1191" T = "0" Pressure = "0" />
		<Point X = "464,6527" Y = "-757,3098" T = "0" Pressure = "0" />
		<Point X = "464,6527" Y = "-758,5005" T = "0" Pressure = "0" />
		<Point X = "464,6527" Y = "-758,5005" T = "0" Pressure = "0" />
		<Point X = "465,8434" Y = "-759,6913" T = "0" Pressure = "0" />
		<Point X = "465,8434" Y = "-759,6913" T = "0" Pressure = "0" />
		<Point X = "465,8434" Y = "-759,6913" T = "0" Pressure = "0" />
		<Point X = "465,8434" Y = "-760,882" T = "0" Pressure = "0" />
		<Point X = "465,8434" Y = "-760,882" T = "0" Pressure = "0" />
		<Point X = "465,8434" Y = "-760,882" T = "0" Pressure = "0" />
		<Point X = "465,8434" Y = "-762,0728" T = "0" Pressure = "0" />
		<Point X = "465,8434" Y = "-763,2635" T = "0" Pressure = "0" />
		<Point X = "465,8434" Y = "-763,2635" T = "0" Pressure = "0" />
		<Point X = "467,0342" Y = "-764,4542" T = "0" Pressure = "0" />
		<Point X = "467,0342" Y = "-764,4542" T = "0" Pressure = "0" />
		<Point X = "467,0342" Y = "-764,4542" T = "0" Pressure = "0" />
		<Point X = "468,2249" Y = "-765,645" T = "0" Pressure = "0" />
		<Point X = "468,2249" Y = "-765,645" T = "0" Pressure = "0" />
		<Point X = "468,2249" Y = "-766,8357" T = "0" Pressure = "0" />
		<Point X = "468,2249" Y = "-768,0264" T = "0" Pressure = "0" />
		<Point X = "468,2249" Y = "-768,0264" T = "0" Pressure = "0" />
		<Point X = "468,2249" Y = "-769,2172" T = "0" Pressure = "0" />
		<Point X = "468,2249" Y = "-769,2172" T = "0" Pressure = "0" />
		<Point X = "468,2249" Y = "-769,2172" T = "0" Pressure = "0" />
		<Point X = "469,4156" Y = "-770,4079" T = "0" Pressure = "0" />
		<Point X = "469,4156" Y = "-771,5986" T = "0" Pressure = "0" />
		<Point X = "469,4156" Y = "-771,5986" T = "0" Pressure = "0" />
		<Point X = "469,4156" Y = "-772,7894" T = "0" Pressure = "0" />
		<Point X = "469,4156" Y = "-772,7894" T = "0" Pressure = "0" />
		<Point X = "469,4156" Y = "-773,9802" T = "0" Pressure = "0" />
		<Point X = "470,6064" Y = "-773,9802" T = "0" Pressure = "0" />
		<Point X = "470,6064" Y = "-775,1709" T = "0" Pressure = "0" />
		<Point X = "470,6064" Y = "-775,1709" T = "0" Pressure = "0" />
		<Point X = "470,6064" Y = "-776,3616" T = "0" Pressure = "0" />
		<Point X = "470,6064" Y = "-777,5524" T = "0" Pressure = "0" />
		<Point X = "470,6064" Y = "-777,5524" T = "0" Pressure = "0" />
		<Point X = "470,6064" Y = "-778,7431" T = "0" Pressure = "0" />
		<Point X = "471,7971" Y = "-778,7431" T = "0" Pressure = "0" />
		<Point X = "471,7971" Y = "-779,9338" T = "0" Pressure = "0" />
		<Point X = "471,7971" Y = "-779,9338" T = "0" Pressure = "0" />
		<Point X = "472,9879" Y = "-779,9338" T = "0" Pressure = "0" />
		<Point X = "472,9879" Y = "-779,9338" T = "0" Pressure = "0" />
		<Point X = "472,9879" Y = "-781,1246" T = "0" Pressure = "0" />
		<Point X = "472,9879" Y = "-781,1246" T = "0" Pressure = "0" />
		<Point X = "472,9879" Y = "-782,3153" T = "0" Pressure = "0" />
		<Point X = "472,9879" Y = "-782,3153" T = "0" Pressure = "0" />
		<Point X = "472,9879" Y = "-783,506" T = "0" Pressure = "0" />
		<Point X = "474,1786" Y = "-783,506" T = "0" Pressure = "0" />
		<Point X = "474,1786" Y = "-783,506" T = "0" Pressure = "0" />
		<Point X = "474,1786" Y = "-784,6968" T = "0" Pressure = "0" />
		<Point X = "474,1786" Y = "-784,6968" T = "0" Pressure = "0" />
		<Point X = "474,1786" Y = "-784,6968" T = "0" Pressure = "0" />
		<Point X = "475,3694" Y = "-785,8875" T = "0" Pressure = "0" />
		<Point X = "475,3694" Y = "-787,0782" T = "0" Pressure = "0" />
		<Point X = "475,3694" Y = "-787,0782" T = "0" Pressure = "0" />
		<Point X = "475,3694" Y = "-787,0782" T = "0" Pressure = "0" />
		<Point X = "475,3694" Y = "-788,269" T = "0" Pressure = "0" />
		<Point X = "475,3694" Y = "-788,269" T = "0" Pressure = "0" />
		<Point X = "475,3694" Y = "-788,269" T = "0" Pressure = "0" />
		<Point X = "476,5601" Y = "-789,4597" T = "0" Pressure = "0" />
		<Point X = "476,5601" Y = "-789,4597" T = "0" Pressure = "0" />
		<Point X = "477,7508" Y = "-790,6505" T = "0" Pressure = "0" />
		<Point X = "477,7508" Y = "-791,8412" T = "0" Pressure = "0" />
		<Point X = "477,7508" Y = "-791,8412" T = "0" Pressure = "0" />
		<Point X = "477,7508" Y = "-791,8412" T = "0" Pressure = "0" />
		<Point X = "477,7508" Y = "-791,8412" T = "0" Pressure = "0" />
		<Point X = "478,9416" Y = "-793,032" T = "0" Pressure = "0" />
		<Point X = "478,9416" Y = "-793,032" T = "0" Pressure = "0" />
		<Point X = "478,9416" Y = "-794,2227" T = "0" Pressure = "0" />
		<Point X = "478,9416" Y = "-794,2227" T = "0" Pressure = "0" />
		<Point X = "478,9416" Y = "-794,2227" T = "0" Pressure = "0" />
		<Point X = "478,9416" Y = "-795,4135" T = "0" Pressure = "0" />
		<Point X = "480,1323" Y = "-795,4135" T = "0" Pressure = "0" />
		<Point X = "480,1323" Y = "-795,4135" T = "0" Pressure = "0" />
		<Point X = "480,1323" Y = "-795,4135" T = "0" Pressure = "0" />
		<Point X = "480,1323" Y = "-797,7949" T = "0" Pressure = "0" />
		<Point X = "480,1323" Y = "-797,7949" T = "0" Pressure = "0" />
		<Point X = "480,1323" Y = "-797,7949" T = "0" Pressure = "0" />
		<Point X = "481,323" Y = "-798,9857" T = "0" Pressure = "0" />
		<Point X = "481,323" Y = "-798,9857" T = "0" Pressure = "0" />
		<Point X = "481,323" Y = "-798,9857" T = "0" Pressure = "0" />
		<Point X = "482,5138" Y = "-800,1764" T = "0" Pressure = "0" />
		<Point X = "482,5138" Y = "-800,1764" T = "0" Pressure = "0" />
		<Point X = "482,5138" Y = "-800,1764" T = "0" Pressure = "0" />
		<Point X = "483,7045" Y = "-801,3671" T = "0" Pressure = "0" />
		<Point X = "483,7045" Y = "-802,5579" T = "0" Pressure = "0" />
		<Point X = "483,7045" Y = "-802,5579" T = "0" Pressure = "0" />
		<Point X = "483,7045" Y = "-802,5579" T = "0" Pressure = "0" />
		<Point X = "484,8953" Y = "-803,7486" T = "0" Pressure = "0" />
		<Point X = "484,8953" Y = "-803,7486" T = "0" Pressure = "0" />
		<Point X = "486,086" Y = "-804,9393" T = "0" Pressure = "0" />
		<Point X = "486,086" Y = "-806,1301" T = "0" Pressure = "0" />
		<Point X = "487,2767" Y = "-807,3208" T = "0" Pressure = "0" />
		<Point X = "488,4675" Y = "-808,5115" T = "0" Pressure = "0" />
		<Point X = "489,6582" Y = "-808,5115" T = "0" Pressure = "0" />
		<Point X = "489,6582" Y = "-809,7023" T = "0" Pressure = "0" />
		<Point X = "490,8489" Y = "-809,7023" T = "0" Pressure = "0" />
		<Point X = "490,8489" Y = "-809,7023" T = "0" Pressure = "0" />
		<Point X = "490,8489" Y = "-809,7023" T = "0" Pressure = "0" />
		<Point X = "490,8489" Y = "-810,8931" T = "0" Pressure = "0" />
		<Point X = "490,8489" Y = "-810,8931" T = "0" Pressure = "0" />
		<Point X = "492,0397" Y = "-812,0838" T = "0" Pressure = "0" />
		<Point X = "492,0397" Y = "-812,0838" T = "0" Pressure = "0" />
		<Point X = "492,0397" Y = "-812,0838" T = "0" Pressure = "0" />
		<Point X = "493,2304" Y = "-812,0838" T = "0" Pressure = "0" />
		<Point X = "493,2304" Y = "-812,0838" T = "0" Pressure = "0" />
		<Point X = "493,2304" Y = "-812,0838" T = "0" Pressure = "0" />
		<Point X = "493,2304" Y = "-813,2745" T = "0" Pressure = "0" />
		<Point X = "493,2304" Y = "-813,2745" T = "0" Pressure = "0" />
		<Point X = "493,2304" Y = "-813,2745" T = "0" Pressure = "0" />
		<Point X = "493,2304" Y = "-813,2745" T = "0" Pressure = "0" />
		<Point X = "494,4212" Y = "-813,2745" T = "0" Pressure = "0" />
		<Point X = "494,4212" Y = "-813,2745" T = "0" Pressure = "0" />
		<Point X = "494,4212" Y = "-813,2745" T = "0" Pressure = "0" />
		<Point X = "494,4212" Y = "-814,4653" T = "0" Pressure = "0" />
		<Point X = "494,4212" Y = "-814,4653" T = "0" Pressure = "0" />
		<Point X = "494,4212" Y = "-814,4653" T = "0" Pressure = "0" />
		<Point X = "495,6119" Y = "-814,4653" T = "0" Pressure = "0" />
		<Point X = "495,6119" Y = "-814,4653" T = "0" Pressure = "0" />
		<Point X = "495,6119" Y = "-814,4653" T = "0" Pressure = "0" />
		<Point X = "495,6119" Y = "-815,656" T = "0" Pressure = "0" />
		<Point X = "495,6119" Y = "-815,656" T = "0" Pressure = "0" />
		<Point X = "495,6119" Y = "-815,656" T = "0" Pressure = "0" />
		<Point X = "496,8026" Y = "-815,656" T = "0" Pressure = "0" />
		<Point X = "496,8026" Y = "-816,8467" T = "0" Pressure = "0" />
		<Point X = "496,8026" Y = "-816,8467" T = "0" Pressure = "0" />
		<Point X = "497,9934" Y = "-816,8467" T = "0" Pressure = "0" />
		<Point X = "497,9934" Y = "-816,8467" T = "0" Pressure = "0" />
		<Point X = "497,9934" Y = "-818,0375" T = "0" Pressure = "0" />
		<Point X = "497,9934" Y = "-818,0375" T = "0" Pressure = "0" />
		<Point X = "499,1841" Y = "-818,0375" T = "0" Pressure = "0" />
		<Point X = "499,1841" Y = "-819,2282" T = "0" Pressure = "0" />
		<Point X = "499,1841" Y = "-819,2282" T = "0" Pressure = "0" />
		<Point X = "500,3748" Y = "-819,2282" T = "0" Pressure = "0" />
		<Point X = "500,3748" Y = "-819,2282" T = "0" Pressure = "0" />
		<Point X = "500,3748" Y = "-820,4189" T = "0" Pressure = "0" />
		<Point X = "500,3748" Y = "-820,4189" T = "0" Pressure = "0" />
		<Point X = "501,5656" Y = "-821,6097" T = "0" Pressure = "0" />
		<Point X = "501,5656" Y = "-821,6097" T = "0" Pressure = "0" />
		<Point X = "501,5656" Y = "-821,6097" T = "0" Pressure = "0" />
		<Point X = "502,7563" Y = "-822,8004" T = "0" Pressure = "0" />
		<Point X = "502,7563" Y = "-822,8004" T = "0" Pressure = "0" />
		<Point X = "502,7563" Y = "-822,8004" T = "0" Pressure = "0" />
		<Point X = "502,7563" Y = "-822,8004" T = "0" Pressure = "0" />
		<Point X = "503,9471" Y = "-823,9911" T = "0" Pressure = "0" />
		<Point X = "503,9471" Y = "-823,9911" T = "0" Pressure = "0" />
		<Point X = "503,9471" Y = "-823,9911" T = "0" Pressure = "0" />
		<Point X = "505,1378" Y = "-825,1819" T = "0" Pressure = "0" />
		<Point X = "505,1378" Y = "-825,1819" T = "0" Pressure = "0" />
		<Point X = "505,1378" Y = "-826,3726" T = "0" Pressure = "0" />
		<Point X = "505,1378" Y = "-826,3726" T = "0" Pressure = "0" />
		<Point X = "505,1378" Y = "-826,3726" T = "0" Pressure = "0" />
		<Point X = "506,3286" Y = "-827,5634" T = "0" Pressure = "0" />
		<Point X = "506,3286" Y = "-827,5634" T = "0" Pressure = "0" />
		<Point X = "506,3286" Y = "-827,5634" T = "0" Pressure = "0" />
		<Point X = "507,5193" Y = "-827,5634" T = "0" Pressure = "0" />
		<Point X = "507,5193" Y = "-828,7542" T = "0" Pressure = "0" />
		<Point X = "507,5193" Y = "-828,7542" T = "0" Pressure = "0" />
		<Point X = "507,5193" Y = "-828,7542" T = "0" Pressure = "0" />
		<Point X = "507,5193" Y = "-828,7542" T = "0" Pressure = "0" />
		<Point X = "508,71" Y = "-828,7542" T = "0" Pressure = "0" />
		<Point X = "508,71" Y = "-829,9449" T = "0" Pressure = "0" />
		<Point X = "508,71" Y = "-829,9449" T = "0" Pressure = "0" />
		<Point X = "508,71" Y = "-829,9449" T = "0" Pressure = "0" />
		<Point X = "508,71" Y = "-829,9449" T = "0" Pressure = "0" />
		<Point X = "508,71" Y = "-829,9449" T = "0" Pressure = "0" />
		<Point X = "508,71" Y = "-831,1356" T = "0" Pressure = "0" />
		<Point X = "508,71" Y = "-831,1356" T = "0" Pressure = "0" />
		<Point X = "508,71" Y = "-831,1356" T = "0" Pressure = "0" />
		<Point X = "508,71" Y = "-831,1356" T = "0" Pressure = "0" />
		<Point X = "508,71" Y = "-831,1356" T = "0" Pressure = "0" />
		<Point X = "508,71" Y = "-831,1356" T = "0" Pressure = "0" />
		<Point X = "508,71" Y = "-831,1356" T = "0" Pressure = "0" />
		<Point X = "508,71" Y = "-831,1356" T = "0" Pressure = "0" />
		<Point X = "508,71" Y = "-831,1356" T = "0" Pressure = "0" />
		<Point X = "508,71" Y = "-831,1356" T = "0" Pressure = "0" />
		<Point X = "508,71" Y = "-831,1356" T = "0" Pressure = "0" />
		<Point X = "508,71" Y = "-831,1356" T = "0" Pressure = "0" />
		<Point X = "508,71" Y = "-831,1356" T = "0" Pressure = "0" />
		<Point X = "508,71" Y = "-831,1356" T = "0" Pressure = "0" />
		<Point X = "508,71" Y = "-831,1356" T = "0" Pressure = "0" />
		<Point X = "508,71" Y = "-831,1356" T = "0" Pressure = "0" />
		<Point X = "508,71" Y = "-831,1356" T = "0" Pressure = "0" />
		<Point X = "508,71" Y = "-831,1356" T = "0" Pressure = "0" />
		<Point X = "508,71" Y = "-831,1356" T = "0" Pressure = "0" />
		<Point X = "508,71" Y = "-831,1356" T = "0" Pressure = "0" />
		<Point X = "508,71" Y = "-831,1356" T = "0" Pressure = "0" />
		<Point X = "508,71" Y = "-831,1356" T = "0" Pressure = "0" />
		<Point X = "508,71" Y = "-831,1356" T = "0" Pressure = "0" />
		<Point X = "508,71" Y = "-831,1356" T = "0" Pressure = "0" />
		<Point X = "508,71" Y = "-831,1356" T = "0" Pressure = "0" />
		<Point X = "508,71" Y = "-831,1356" T = "0" Pressure = "0" />
		<Point X = "508,71" Y = "-831,1356" T = "0" Pressure = "0" />
		<Point X = "508,71" Y = "-831,1356" T = "0" Pressure = "0" />
		<Point X = "508,71" Y = "-831,1356" T = "0" Pressure = "0" />
		<Point X = "508,71" Y = "-831,1356" T = "0" Pressure = "0" />
		<Point X = "508,71" Y = "-831,1356" T = "0" Pressure = "0" />
		<Point X = "508,71" Y = "-831,1356" T = "0" Pressure = "0" />
		<Point X = "508,71" Y = "-831,1356" T = "0" Pressure = "0" />
		<Point X = "508,71" Y = "-831,1356" T = "0" Pressure = "0" />
		<Point X = "508,71" Y = "-831,1356" T = "0" Pressure = "0" />
		<Point X = "508,71" Y = "-831,1356" T = "0" Pressure = "0" />
		<Point X = "508,71" Y = "-831,1356" T = "0" Pressure = "0" />
		<Point X = "508,71" Y = "-831,1356" T = "0" Pressure = "0" />
		<Point X = "508,71" Y = "-831,1356" T = "0" Pressure = "0" />
		<Point X = "508,71" Y = "-831,1356" T = "0" Pressure = "0" />
		<Point X = "508,71" Y = "-831,1356" T = "0" Pressure = "0" />
		<Point X = "508,71" Y = "-831,1356" T = "0" Pressure = "0" />
		<Point X = "508,71" Y = "-831,1356" T = "0" Pressure = "0" />
		<Point X = "508,71" Y = "-831,1356" T = "0" Pressure = "0" />
		<Point X = "508,71" Y = "-831,1356" T = "0" Pressure = "0" />
		<Point X = "508,71" Y = "-831,1356" T = "0" Pressure = "0" />
		<Point X = "508,71" Y = "-831,1356" T = "0" Pressure = "0" />
		<Point X = "508,71" Y = "-831,1356" T = "0" Pressure = "0" />
		<Point X = "508,71" Y = "-831,1356" T = "0" Pressure = "0" />
		<Point X = "508,71" Y = "-831,1356" T = "0" Pressure = "0" />
		<Point X = "508,71" Y = "-831,1356" T = "0" Pressure = "0" />
		<Point X = "508,71" Y = "-831,1356" T = "0" Pressure = "0" />
		<Point X = "508,71" Y = "-831,1356" T = "0" Pressure = "0" />
		<Point X = "508,71" Y = "-831,1356" T = "0" Pressure = "0" />
		<Point X = "508,71" Y = "-831,1356" T = "0" Pressure = "0" />
		<Point X = "508,71" Y = "-831,1356" T = "0" Pressure = "0" />
		<Point X = "508,71" Y = "-831,1356" T = "0" Pressure = "0" />
		<Point X = "508,71" Y = "-831,1356" T = "0" Pressure = "0" />
		<Point X = "508,71" Y = "-831,1356" T = "0" Pressure = "0" />
		<Point X = "508,71" Y = "-831,1356" T = "0" Pressure = "0" />
		<Point X = "508,71" Y = "-831,1356" T = "0" Pressure = "0" />
		<Point X = "508,71" Y = "-831,1356" T = "0" Pressure = "0" />
		<Point X = "508,71" Y = "-831,1356" T = "0" Pressure = "0" />
		<Point X = "508,71" Y = "-831,1356" T = "0" Pressure = "0" />
		<Point X = "508,71" Y = "-831,1356" T = "0" Pressure = "0" />
		<Point X = "508,71" Y = "-831,1356" T = "0" Pressure = "0" />
		<Point X = "508,71" Y = "-831,1356" T = "0" Pressure = "0" />
		<Point X = "508,71" Y = "-831,1356" T = "0" Pressure = "0" />
		<Point X = "508,71" Y = "-831,1356" T = "0" Pressure = "0" />
		<Point X = "508,71" Y = "-831,1356" T = "0" Pressure = "0" />
		<Point X = "508,71" Y = "-831,1356" T = "0" Pressure = "0" />
		<Point X = "508,71" Y = "-831,1356" T = "0" Pressure = "0" />
		<Point X = "508,71" Y = "-831,1356" T = "0" Pressure = "0" />
		<Point X = "508,71" Y = "-831,1356" T = "0" Pressure = "0" />
		<Point X = "508,71" Y = "-831,1356" T = "0" Pressure = "0" />
		<Point X = "508,71" Y = "-831,1356" T = "0" Pressure = "0" />
		<Point X = "508,71" Y = "-831,1356" T = "0" Pressure = "0" />
		<Point X = "508,71" Y = "-831,1356" T = "0" Pressure = "0" />
		<Point X = "508,71" Y = "-831,1356" T = "0" Pressure = "0" />
		<Point X = "508,71" Y = "-831,1356" T = "0" Pressure = "0" />
		<Point X = "508,71" Y = "-831,1356" T = "0" Pressure = "0" />
		<Point X = "508,71" Y = "-831,1356" T = "0" Pressure = "0" />
		<Point X = "508,71" Y = "-831,1356" T = "0" Pressure = "0" />
		<Point X = "508,71" Y = "-831,1356" T = "0" Pressure = "0" />
		<Point X = "508,71" Y = "-831,1356" T = "0" Pressure = "0" />
		<Point X = "508,71" Y = "-831,1356" T = "0" Pressure = "0" />
		<Point X = "508,71" Y = "-831,1356" T = "0" Pressure = "0" />
		<Point X = "508,71" Y = "-831,1356" T = "0" Pressure = "0" />
		<Point X = "508,71" Y = "-831,1356" T = "0" Pressure = "0" />
		<Point X = "508,71" Y = "-831,1356" T = "0" Pressure = "0" />
		<Point X = "508,71" Y = "-831,1356" T = "0" Pressure = "0" />
		<Point X = "508,71" Y = "-831,1356" T = "0" Pressure = "0" />
		<Point X = "508,71" Y = "-831,1356" T = "0" Pressure = "0" />
		<Point X = "508,71" Y = "-831,1356" T = "0" Pressure = "0" />
		<Point X = "508,71" Y = "-831,1356" T = "0" Pressure = "0" />
		<Point X = "508,71" Y = "-831,1356" T = "0" Pressure = "0" />
		<Point X = "508,71" Y = "-831,1356" T = "0" Pressure = "0" />
		<Point X = "508,71" Y = "-831,1356" T = "0" Pressure = "0" />
		<Point X = "508,71" Y = "-831,1356" T = "0" Pressure = "0" />
		<Point X = "508,71" Y = "-831,1356" T = "0" Pressure = "0" />
		<Point X = "508,71" Y = "-831,1356" T = "0" Pressure = "0" />
		<Point X = "508,71" Y = "-831,1356" T = "0" Pressure = "0" />
		<Point X = "508,71" Y = "-831,1356" T = "0" Pressure = "0" />
		<Point X = "508,71" Y = "-831,1356" T = "0" Pressure = "0" />
		<Point X = "508,71" Y = "-831,1356" T = "0" Pressure = "0" />
		<Point X = "508,71" Y = "-831,1356" T = "0" Pressure = "0" />
		<Point X = "508,71" Y = "-831,1356" T = "0" Pressure = "0" />
		<Point X = "508,71" Y = "-831,1356" T = "0" Pressure = "0" />
		<Point X = "508,71" Y = "-831,1356" T = "0" Pressure = "0" />
		<Point X = "508,71" Y = "-831,1356" T = "0" Pressure = "0" />
		<Point X = "508,71" Y = "-831,1356" T = "0" Pressure = "0" />
		<Point X = "508,71" Y = "-831,1356" T = "0" Pressure = "0" />
		<Point X = "508,71" Y = "-831,1356" T = "0" Pressure = "0" />
		<Point X = "508,71" Y = "-831,1356" T = "0" Pressure = "0" />
	</Stroke>
</Gesture>
